fedsim/__init__.py
fedsim/losses.py
fedsim/lr_schedulers.py
fedsim/scores.py
fedsim/datasets/__init__.py
fedsim/distributed/__init__.py
fedsim/distributed/centralized/__init__.py
fedsim/distributed/centralized/centralized_fl_algorithm.py
fedsim/distributed/centralized/compression/__init__.py
fedsim/distributed/centralized/privacy/__init__ copy.py
fedsim/distributed/centralized/privacy/__init__.py
fedsim/distributed/centralized/training/__init__.py
fedsim/distributed/centralized/training/adabest.py
fedsim/distributed/centralized/training/fedavg.py
fedsim/distributed/centralized/training/fedavgm.py
fedsim/distributed/centralized/training/feddf.py
fedsim/distributed/centralized/training/feddyn.py
fedsim/distributed/centralized/training/fednova.py
fedsim/distributed/centralized/training/fedprox.py
fedsim/distributed/centralized/training/utils.py
fedsim/distributed/data_management/__init__.py
fedsim/distributed/data_management/basic_data_manager.py
fedsim/distributed/data_management/data_manager.py
fedsim/distributed/data_management/utils.py
fedsim/distributed/decentralized/__init__.py
fedsim/distributed/decentralized/compression/__init__.py
fedsim/distributed/decentralized/privacy/__init__.py
fedsim/distributed/decentralized/training/__init__.py
fedsim/local/__init__.py
fedsim/local/training/__init__.py
fedsim/local/training/_inference.py
fedsim/local/training/_training.py
fedsim/local/training/inference.py
fedsim/local/training/step_closures.py
fedsim/local/training/training.py
fedsim/lr_schedulers/__init__.py
fedsim/lr_schedulers/lr_schedulers.py
fedsim/models/__init__.py
fedsim/models/mcmahan_nets.py
fedsim/models/simple_models.py
fedsim/models/utils.py
fedsim/utils/__init__.py
fedsim/utils/_convert_parameters.py
fedsim/utils/_dict_opts.py
fedsim/utils/_importing.py
fedsim/utils/_metric_scores.py
fedsim/utils/_seed.py
fedsim/utils/aggregators.py
fedsim/utils/convert_parameters.py
fedsim/utils/dict_ops.py
fedsim/utils/import_utils.py
fedsim/utils/random_utils.py
fedsim-0.9.0.dist-info/LICENSE
fedsim-0.9.0.dist-info/METADATA
fedsim-0.9.0.dist-info/WHEEL
fedsim-0.9.0.dist-info/entry_points.txt
fedsim-0.9.0.dist-info/top_level.txt
fedsim-0.9.0.dist-info/RECORD
