Metadata-Version: 2.1
Name: fedsim
Version: 0.9.0
Summary: Generic Federated Learning Simulator with PyTorch
Home-page: https://github.com/varnio/fedsim
Author: Farshid Varno
Author-email: fr.varno@gmail.com
License: Apache-2.0
Project-URL: Documentation, https://fedsim.varnio.com/
Project-URL: Changelog, https://fedsim.varnio.com/en/latest/changelog.html
Project-URL: Issue Tracker, https://github.com/varnio/fedsim/issues
Keywords: pytorch,neural networks,template,federated,federated         learning,deep learning,distributed learning
Platform: any
Classifier: Development Status :: 2 - Pre-Alpha
Classifier: Intended Audience :: Developers
Classifier: Intended Audience :: Education
Classifier: License :: OSI Approved :: Apache Software License
Classifier: Operating System :: Unix
Classifier: Operating System :: POSIX
Classifier: Operating System :: Microsoft :: Windows
Classifier: Intended Audience :: Science/Research
Classifier: Intended Audience :: Information Technology
Classifier: License :: OSI Approved :: Apache Software License
Classifier: Topic :: Scientific/Engineering
Classifier: Topic :: Scientific/Engineering :: Mathematics
Classifier: Topic :: Scientific/Engineering :: Artificial Intelligence
Classifier: Topic :: Software Development
Classifier: Topic :: Software Development :: Libraries
Classifier: Topic :: Software Development :: Libraries :: Python Modules
Classifier: Topic :: System :: Distributed Computing
Classifier: Programming Language :: Python
Classifier: Programming Language :: Python :: 3
Classifier: Programming Language :: Python :: 3 :: Only
Classifier: Programming Language :: Python :: 3.9
Classifier: Programming Language :: Python :: 3.10
Classifier: Topic :: Utilities
Requires-Python: >=3.6
License-File: LICENSE
Requires-Dist: click
Requires-Dist: numpy
Requires-Dist: sklearn
Requires-Dist: scikit-optimize
Requires-Dist: tqdm
Requires-Dist: torch
Requires-Dist: torchvision
Requires-Dist: tensorboard
Requires-Dist: pyyaml
Requires-Dist: logall
Provides-Extra: test
Requires-Dist: pytest ; extra == 'test'
Requires-Dist: pytest-cov ; extra == 'test'
Requires-Dist: codecov ; extra == 'test'
